timesmash/XHMMClustering.py
timesmash/__init__.py
timesmash/_version.py
timesmash/clustering.py
timesmash/cynet.py
timesmash/distance.py
timesmash/featurizer.py
timesmash/quantizer.py
timesmash/scripts.py
timesmash/smash.py
timesmash/utils.py
timesmash/bin/Quantizer
timesmash/bin/XgenESeSS
timesmash/bin/XgenESeSS_FOR
timesmash/bin/XgenESeSS_cynet
timesmash/bin/corr
timesmash/bin/cynet
timesmash/bin/embed
timesmash/bin/flexroc
timesmash/bin/genESeSS
timesmash/bin/genESeSS_feature
timesmash/bin/json_read
timesmash/bin/llk
timesmash/bin/llk_state
timesmash/bin/llk_yi
timesmash/bin/lsmash
timesmash/bin/proc
timesmash/bin/serializer
timesmash/bin/smash
timesmash/bin/smashmatch
timesmash-0.2.26.dist-info/LICENSE
timesmash-0.2.26.dist-info/METADATA
timesmash-0.2.26.dist-info/WHEEL
timesmash-0.2.26.dist-info/top_level.txt
timesmash-0.2.26.dist-info/RECORD
