Metadata-Version: 2.1
Name: timesmash
Version: 0.2.26
Summary: Quantifier of universal similarity amongst arbitrary data streams without a priori knowledge, features, or training.
Home-page: https://github.com/zeroknowledgediscovery/timesmash
Maintainer: Victor Rotaru
Maintainer-email: virotaru@uchicago.edu
Keywords: timeseries
Classifier: Programming Language :: Python :: 3
License-File: LICENSE
Requires-Dist: pandas
Requires-Dist: numpy
Requires-Dist: scikit-learn
